vdf_io/__init__.py
vdf_io/constants.py
vdf_io/export_vdf_cli.py
vdf_io/import_vdf_cli.py
vdf_io/marqo_vespa_util.py
vdf_io/meta_types.py
vdf_io/names.py
vdf_io/print_help_rec.py
vdf_io/turbopuffer.py
vdf_io/util.py
vdf_io/export_vdf/__init__.py
vdf_io/export_vdf/astradb_export.py
vdf_io/export_vdf/azureai_export.py
vdf_io/export_vdf/chroma_export.py
vdf_io/export_vdf/kdbai_export.py
vdf_io/export_vdf/lancedb_export.py
vdf_io/export_vdf/milvus_export.py
vdf_io/export_vdf/pinecone_export.py
vdf_io/export_vdf/qdrant_export.py
vdf_io/export_vdf/turbopuffer_export.py
vdf_io/export_vdf/txtai_export.py
vdf_io/export_vdf/vdb_export_cls.py
vdf_io/export_vdf/vertexai_vector_search_export.py
vdf_io/export_vdf/vespa_export.py
vdf_io/export_vdf/weaviate_export.py
vdf_io/import_vdf/__init__.py
vdf_io/import_vdf/astradb_import.py
vdf_io/import_vdf/azureai_import.py
vdf_io/import_vdf/chroma_import.py
vdf_io/import_vdf/kdbai_import.py
vdf_io/import_vdf/lancedb_import.py
vdf_io/import_vdf/milvus_import.py
vdf_io/import_vdf/pinecone_import.py
vdf_io/import_vdf/qdrant_import.py
vdf_io/import_vdf/turbopuffer_import.py
vdf_io/import_vdf/vdf_import_cls.py
vdf_io/import_vdf/vertexai_vector_search_import.py
vdf_io/scripts/__init__.py
vdf_io/scripts/bump_version.py
vdf_io/scripts/check_for_updates.py
vdf_io/scripts/consolidate_parquet.py
vdf_io/scripts/count_rows.py
vdf_io/scripts/count_rows_hf.py
vdf_io/scripts/get_id_list.py
vdf_io/scripts/push_to_hub_vdf.py
vdf_io/scripts/reembed.py
vdf_io-0.1.248.dist-info/LICENSE
vdf_io-0.1.248.dist-info/METADATA
vdf_io-0.1.248.dist-info/WHEEL
vdf_io-0.1.248.dist-info/entry_points.txt
vdf_io-0.1.248.dist-info/top_level.txt
vdf_io-0.1.248.dist-info/RECORD
