Metadata-Version: 2.1
Name: vdf-io
Version: 0.1.248
Summary: This library uses a universal format for vector datasets to easily export and import data from all vector databases.
Author: Dhruv Anand
Author-email: dhruv.anand@ainorthstartech.com
License: Apache 2.0
License-File: LICENSE
Requires-Dist: numpy
Requires-Dist: pandas
Requires-Dist: pinecone-client[grpc] (~=4.0)
Requires-Dist: pyarrow
Requires-Dist: qdrant-client
Requires-Dist: tqdm
Requires-Dist: python-dotenv
Requires-Dist: huggingface-hub
Requires-Dist: pymilvus (>=2.3.6)
Requires-Dist: openai (>=1.10.0)
Requires-Dist: litellm (>=1.20.0)
Requires-Dist: google-cloud-aiplatform
Requires-Dist: google-api-python-client
Requires-Dist: google-auth-httplib2
Requires-Dist: google-auth-oauthlib
Requires-Dist: ratelimit
Requires-Dist: backoff
Requires-Dist: kdbai-client
Requires-Dist: sentry-sdk[opentelemetry]
Requires-Dist: halo
Requires-Dist: sentence-transformers (>=2.6.1)
Requires-Dist: pyvespa
Requires-Dist: lancedb
Requires-Dist: chromadb
Requires-Dist: txtai
Requires-Dist: weaviate-client (>=4.0.0)
Requires-Dist: astrapy
Requires-Dist: cassandra-driver
Requires-Dist: tenacity
Requires-Dist: torch
Requires-Dist: twine
Requires-Dist: datasets (>=2.19.0,~=2.16)
Requires-Dist: mlx-embedding-models
Requires-Dist: azure-search-documents
Requires-Dist: azure-identity
Requires-Dist: turbopuffer[fast]
Requires-Dist: psycopg2
